yearly_insights_parser/__init__.py
yearly_insights_parser/main.py
yearly_insights_parser/prompts.py
yearly_insights_parser-2025.12.21101922.dist-info/METADATA
yearly_insights_parser-2025.12.21101922.dist-info/WHEEL
yearly_insights_parser-2025.12.21101922.dist-info/top_level.txt
yearly_insights_parser-2025.12.21101922.dist-info/RECORD
