Metadata-Version: 2.4
Name: yearly-insights-parser
Version: 2025.12.21101922
Summary: A new package that analyzes user-provided text summaries of yearly breakdowns (e.g., financial reports, project post-mortems, or performance reviews) and extracts structured insights. It uses an LLM t
Author-email: yearly-insights-parser <hi@eugene.plus>
License: MIT
Project-URL: Homepage, https://github.com/chigwell/yearly-insights-parser
Requires-Python: >=3.9
Requires-Dist: langchain-llm7>=0.0.0
Requires-Dist: llmatch-messages>=0.0.0
Requires-Dist: langchain-core>=0.3.0
